openapi_gen/__init__.py
openapi_gen/swagger.py
openapi_gen/lib/__init__.py
openapi_gen/lib/constants.py
openapi_gen/lib/dependency.py
openapi_gen/lib/endpoint.py
openapi_gen/lib/metadata.py
openapi_gen/lib/schema.py
openapi_gen/lib/security.py
openapi_gen/lib/utils.py
openapi_gen/lib/wrappers.py
openapi_gen/resources/__init__.py
openapi_gen/resources/swagger.pkl
openapi_gen-1.1.58.dist-info/LICENSE
openapi_gen-1.1.58.dist-info/METADATA
openapi_gen-1.1.58.dist-info/WHEEL
openapi_gen-1.1.58.dist-info/top_level.txt
openapi_gen-1.1.58.dist-info/RECORD
